save_scummer/__init__.py
save_scummer/backup.py
save_scummer/cli.py
save_scummer/config.py
save_scummer/py.typed
save_scummer/utils.py
save_scummer-0.1.1.dist-info/METADATA
save_scummer-0.1.1.dist-info/WHEEL
save_scummer-0.1.1.dist-info/entry_points.txt
save_scummer-0.1.1.dist-info/licenses/LICENSE
save_scummer-0.1.1.dist-info/RECORD
