Metadata-Version: 2.4
Name: save-scummer
Version: 0.1.1
Summary: A simple CLI utility to backup and restore game saves
Project-URL: Source code, https://github.com/JWCook/save-scummer
Author: Jordan Cook
License-Expression: MIT
License-File: LICENSE
Keywords: backup,game,restore,roguelike,roguelite,save
Classifier: Development Status :: 3 - Alpha
Classifier: Environment :: Console
Classifier: License :: OSI Approved :: MIT License
Classifier: Programming Language :: Python :: 3
Requires-Python: >=3.8
Requires-Dist: click-completion
Requires-Dist: click>=7.0
Requires-Dist: halo
Requires-Dist: platformdirs
Requires-Dist: python-dateutil
Requires-Dist: python-slugify
Requires-Dist: pytimeparse
Requires-Dist: pyyaml>=5.0
Requires-Dist: tabulate
